pyawake/IndexingPython.py
pyawake/IndexingSpark.py
pyawake/Searching.py
pyawake/Visualizing.py
pyawake/__init__.py
pyawake-0.0.5.dist-info/LICENSE
pyawake-0.0.5.dist-info/METADATA
pyawake-0.0.5.dist-info/WHEEL
pyawake-0.0.5.dist-info/top_level.txt
pyawake-0.0.5.dist-info/RECORD
