Metadata-Version: 2.1
Name: pyawake
Version: 0.0.5
Summary: A pyawake library
Home-page: https://github.com/singh96aman/pyawake
Author: Aman Singh Thakur
Author-email: singh96aman@gmail.com
License: UNKNOWN
Platform: UNKNOWN
Classifier: Programming Language :: Python :: 3
Classifier: License :: OSI Approved :: MIT License
Classifier: Operating System :: OS Independent
